mutual_info/__init__.py
mutual_info/mutual_info.py
mutual_info-0.31.dist-info/LICENSE
mutual_info-0.31.dist-info/METADATA
mutual_info-0.31.dist-info/WHEEL
mutual_info-0.31.dist-info/top_level.txt
mutual_info-0.31.dist-info/RECORD
