Metadata-Version: 2.1
Name: mutual-info
Version: 0.31
Summary: Putting GaelVaraquaux's gist in a repo. Mutual information calculation utils.
Home-page: https://github.com/mutualinfo/mutual_info
License: UNKNOWN
Platform: UNKNOWN
Requires-Dist: numpy
Requires-Dist: scipy
Requires-Dist: scikit-learn
